plsdsm/__init__.py
plsdsm/plsds.py
plsdsm-0.0.1.dist-info/METADATA
plsdsm-0.0.1.dist-info/WHEEL
plsdsm-0.0.1.dist-info/top_level.txt
plsdsm-0.0.1.dist-info/RECORD
