Metadata-Version: 2.1
Name: plsdsm
Version: 0.0.1
Summary: A Python package for Partial Least Squares
Home-page: UNKNOWN
Author: Soulala Achraf, Souidi Yassine, Chafiqui Youssef, Eddamir Amine
Author-email: <achrafs758@gmail.com>
License: UNKNOWN
Keywords: python,regression,PLS,classification,p-value,correlation
Platform: UNKNOWN
Classifier: Development Status :: 1 - Planning
Classifier: Intended Audience :: Developers
Classifier: Programming Language :: Python :: 3
Classifier: Operating System :: Unix
Classifier: Operating System :: MacOS :: MacOS X
Classifier: Operating System :: Microsoft :: Windows
Requires-Dist: pandas
Requires-Dist: numpy
Requires-Dist: statsmodels
